README.md
setup.cfg
setup.py
retic/__init__.py
retic/cfg.py
retic.egg-info/PKG-INFO
retic.egg-info/SOURCES.txt
retic.egg-info/dependency_links.txt
retic.egg-info/requires.txt
retic.egg-info/top_level.txt
retic/lib/__init__.py
retic/lib/retic.py
retic/lib/hooks/__init__.py
retic/lib/hooks/middlewares/__init__.py
retic/lib/hooks/middlewares/cors.py
retic/lib/hooks/responses/__init__.py
retic/lib/hooks/responses/next.py
retic/lib/hooks/responses/request.py
retic/lib/hooks/responses/response.py
retic/lib/hooks/system/__init__.py
retic/lib/hooks/system/env.py
retic/lib/router/__init__.py
retic/lib/router/httpmethod.py
retic/lib/router/layer.py
retic/lib/router/route.py
retic/lib/router/router.py
retic/lib/translation/__init__.py
retic/lib/translation/gettext/__init__.py
retic/lib/translation/gettext/gettext.py
retic/services/__init__.py
retic/services/responses.py
retic/services/validations.py
retic/services/core/__init__.py
retic/services/core/general.py
retic/services/core/msgfmt.py
retic/services/exceptions/__init__.py
retic/services/exceptions/exceptions.py
retic/services/general/__init__.py
retic/services/general/json.py
retic/services/general/time.py
retic/services/general/urls.py
test/test_lib_hooks_responses_request.py
test/test_lib_hooks_responses_response.py
test/test_lib_retic.py
test/test_lib_router_httpmethod.py