Metadata-Version: 2.1
Name: retic
Version: 0.0.15
Summary: Fastest, easiest and simple web framework for Python.
Home-page: https://github.com/reticpy/retic
Author: Braian Staimer
Author-email: braianflorian@gmail.com
License: MIT
Download-URL: https://github.com/reticpy/retic/archive/0.0.15.tar.gz
Keywords: PYTHON,WEB FRAMEWORK,MACHINE LEARNING WEB FRAMEWORK
Platform: UNKNOWN
Classifier: Development Status :: 4 - Beta
Classifier: Intended Audience :: Developers
Classifier: Topic :: Software Development :: Build Tools
Classifier: License :: OSI Approved :: MIT License
Classifier: Programming Language :: Python
Classifier: Programming Language :: Python :: 2
Classifier: Programming Language :: Python :: 2.7
Classifier: Programming Language :: Python :: 3
Classifier: Programming Language :: Python :: 3.5
Classifier: Programming Language :: Python :: 3.6
Classifier: Programming Language :: Python :: 3.7
Classifier: Programming Language :: Python :: 3.8
